yfcc100m/__init__.py
yfcc100m/convert.py
yfcc100m/convert_metadata.py
yfcc100m/download.py
yfcc100m/tools.py
yfcc100m/vars.py
yfcc100m-1.0.1.dist-info/LICENSE
yfcc100m-1.0.1.dist-info/METADATA
yfcc100m-1.0.1.dist-info/WHEEL
yfcc100m-1.0.1.dist-info/top_level.txt
yfcc100m-1.0.1.dist-info/RECORD
