Metadata-Version: 2.1
Name: yfcc100m
Version: 1.0.1
Summary: Download the YFCC100m dataset without going insane.
Home-page: UNKNOWN
Author: Joachim Folz
Author-email: joachim.folz@dfki.de
License: MIT
Project-URL: Documentation, https://gitlab.com/jfolz/yfcc100m/blob/master/README.rst
Project-URL: Source, https://gitlab.com/jfolz/yfcc100m
Project-URL: Tracker, https://gitlab.com/jfolz/yfcc100m/issues
Keywords: yfcc100m yfcc yahoo flickr creative commons 100 million dataset data set download
Platform: UNKNOWN
Classifier: Development Status :: 5 - Production/Stable
Classifier: Intended Audience :: Science/Research
Classifier: Programming Language :: Python :: 3
Classifier: License :: OSI Approved :: MIT License
Requires-Python: >=3.6
Requires-Dist: boto3 (<2.0.0,>=1.11.0)
Requires-Dist: botocore (<2.0.0,>=1.14.0)
Requires-Dist: datadings (<4.0.0,>=3.1.0)
Requires-Dist: numpy (<2.0.0,>=1.17.0)
Requires-Dist: Pillow (>=7.0.0)
Requires-Dist: simplejpeg (>=1.4.1)
Requires-Dist: tqdm (<5.0.0,>=4.23.0)
